wikibase_api/__init__.py
wikibase_api/__version__.py
wikibase_api/api.py
wikibase_api/models/__init__.py
wikibase_api/models/alias.py
wikibase_api/models/claim.py
wikibase_api/models/description.py
wikibase_api/models/entity.py
wikibase_api/models/label.py
wikibase_api/models/qualifier.py
wikibase_api/models/reference.py
wikibase_api/utils/case_conversion.py
wikibase_api/utils/config.py
wikibase_api/utils/exceptions.py
wikibase_api/utils/validate_value.py
wikibase_api/wikibase_api.py
wikibase_api-0.1.1.dist-info/LICENSE
wikibase_api-0.1.1.dist-info/LICENSE-APACHE-2.0
wikibase_api-0.1.1.dist-info/LICENSE-GPL-3.0
wikibase_api-0.1.1.dist-info/WHEEL
wikibase_api-0.1.1.dist-info/METADATA
wikibase_api-0.1.1.dist-info/RECORD
