Metadata-Version: 2.1
Name: wikibase-api
Version: 0.1.1
Summary: Wrapper library for the Wikibase API
Home-page: https://github.com/samuelmeuli/wikibase-api
Keywords: wikibase,wikidata,bot,api,wrapper
Author: Samuel Meuli
Author-email: me@samuelmeuli.com
Requires-Python: >=3.6,<4.0
Classifier: Intended Audience :: Developers
Classifier: Programming Language :: Python :: 3
Classifier: Programming Language :: Python :: 3.6
Classifier: Programming Language :: Python :: 3.7
Classifier: Topic :: Internet
Classifier: Topic :: Internet :: WWW/HTTP :: Dynamic Content :: Wiki
Classifier: Topic :: Software Development :: Libraries :: Python Modules
Requires-Dist: requests (>=2.20,<3.0)
Requires-Dist: requests-oauthlib (>=1.0,<2.0)
Project-URL: Documentation, https://wikibase-api.readthedocs.io
Project-URL: Repository, https://github.com/samuelmeuli/wikibase-api
